plotprimes/__init__.py
plotprimes/plotprimes.py
plotprimes-1.0.1.dist-info/licenses/LICENSE
plotprimes-1.0.1.dist-info/METADATA
plotprimes-1.0.1.dist-info/WHEEL
plotprimes-1.0.1.dist-info/entry_points.txt
plotprimes-1.0.1.dist-info/top_level.txt
plotprimes-1.0.1.dist-info/RECORD
