Metadata-Version: 2.4
Name: plotprimes
Version: 1.0.1
Summary: Plot prime numbers on a polar coordinate system
Author-email: Josh Tompkin <jtompkin-dev@pm.me>
Requires-Python: >=3.13
License-File: LICENSE
Requires-Dist: matplotlib
Dynamic: license-file
